yamet/__init__.py
yamet/__main__.py
yamet/analysis/similarity.py
yamet/analysis/symmetry.py
yamet/chemistry/data.py
yamet/chemistry/utils.py
yamet/collectors/singles.py
yamet/collectors/trajectories.py
yamet/collectors/utils.py
yamet/common/utils.py
yamet/generation/inputs.py
yamet/generation/mlsets.py
yamet/hull/hull.py
yamet/machine_learning/clustering.py
yamet/maths/routines.cpp
yamet/maths/routines.hpp
yamet/maths/routines.py
yamet/plotting/routines.py
yamet/py.typed
yamet/workflows/vasp/getters.py
yamet/workflows/vasp/handlers.py
yamet/workflows/vasp/high_throughput.py
yamet-0.0.2.dist-info/LICENSE
yamet-0.0.2.dist-info/METADATA
yamet-0.0.2.dist-info/WHEEL
yamet-0.0.2.dist-info/entry_points.txt
yamet-0.0.2.dist-info/RECORD
