Metadata-Version: 2.1
Name: yamet
Version: 0.0.2
Summary: YAMET
Home-page: https://github.com/benedictsaunders/yamet
License: MIT
Author: Benedict Saunders
Author-email: benedictsaunders@gmail.com
Requires-Python: >=3.7,<4.0
Classifier: Development Status :: 1 - Planning
Classifier: License :: OSI Approved :: MIT License
Classifier: Programming Language :: Python :: 3
Classifier: Programming Language :: Python :: 3.7
Classifier: Programming Language :: Python :: 3.8
Classifier: Programming Language :: Python :: 3.9
Classifier: Programming Language :: Python :: 3.10
Classifier: Programming Language :: Python :: 3.11
Requires-Dist: click (>=8.0.1)
Project-URL: Changelog, https://github.com/benedictsaunders/yamet/releases
Project-URL: Documentation, https://yamet.readthedocs.io
Project-URL: Repository, https://github.com/benedictsaunders/yamet
